runly/__init__.py
runly/__main__.py
runly/cli.py
runly/commands.py
runly/exceptions.py
runly/parser.py
runly/runner.py
runly/utils.py
runly-0.1.1.dist-info/METADATA
runly-0.1.1.dist-info/WHEEL
runly-0.1.1.dist-info/entry_points.txt
runly-0.1.1.dist-info/licenses/LICENSE
runly-0.1.1.dist-info/RECORD
